LICENSE
MANIFEST.in
README.md
setup.cfg
setup.py
ipywidget_pivot_table/__init__.py
ipywidget_pivot_table/_config.py
ipywidget_pivot_table/_options.py
ipywidget_pivot_table/_sample.py
ipywidget_pivot_table/_state.py
ipywidget_pivot_table/_version.py
ipywidget_pivot_table/_widget_box_pivot.py
ipywidget_pivot_table/_widget_box_pivotui.py
ipywidget_pivot_table/_widget_pivot.py
ipywidget_pivot_table/_widget_pivotui.py
ipywidget_pivot_table/_wrapper.py
ipywidget_pivot_table.egg-info/PKG-INFO
ipywidget_pivot_table.egg-info/SOURCES.txt
ipywidget_pivot_table.egg-info/dependency_links.txt
ipywidget_pivot_table.egg-info/not-zip-safe
ipywidget_pivot_table.egg-info/requires.txt
ipywidget_pivot_table.egg-info/top_level.txt
ipywidget_pivot_table/api/pivot.json
ipywidget_pivot_table/api/pivotui.json
ipywidget_pivot_table/data/iris.csv
ipywidget_pivot_table/data/mps.csv
ipywidget_pivot_table/data/tips.csv
ipywidget_pivot_table/data/weather.csv
ipywidget_pivot_table/markdown/pivotui.md
ipywidget_pivot_table/static/extension.js
ipywidget_pivot_table/static/index.js
ipywidget_pivot_table/static/index.js.map