Metadata-Version: 1.1
Name: ipywidget-pivot-table
Version: 0.1.4
Summary: This is a jupyter widget (or ipywidget) wrapping the very convenient pivotTable.js library.
Home-page: https://github.com/PierreMarion23/pivot-table-widget
Author: PierreMarion23
Author-email: pierre23.marion@free.fr
License: UNKNOWN
Keywords: ipython,jupyter,widgets
Platform: UNKNOWN
Classifier: Development Status :: 4 - Beta
Classifier: Framework :: IPython
Classifier: Intended Audience :: Developers
Classifier: Intended Audience :: Science/Research
Classifier: Topic :: Multimedia :: Graphics
Classifier: Programming Language :: Python :: 2
Classifier: Programming Language :: Python :: 2.7
Classifier: Programming Language :: Python :: 3
Classifier: Programming Language :: Python :: 3.3
Classifier: Programming Language :: Python :: 3.4
Classifier: Programming Language :: Python :: 3.5
